cyber_record/__init__.py
cyber_record/common.py
cyber_record/main.py
cyber_record/query.py
cyber_record/reader.py
cyber_record/record.py
cyber_record/record_exception.py
cyber_record/viewer.py
cyber_record/writer.py
cyber_record/cyber/__init__.py
cyber_record/cyber/proto/__init__.py
cyber_record/cyber/proto/proto_desc_pb2.py
cyber_record/cyber/proto/record_pb2.py
cyber_record/file_object/__init__.py
cyber_record/file_object/chunk.py
cyber_record/file_object/chunk_header.py
cyber_record/file_object/header.py
cyber_record/file_object/single_index.py
cyber_record_mod-0.1.14.dist-info/licenses/LICENSE
cyber_record_mod-0.1.14.dist-info/METADATA
cyber_record_mod-0.1.14.dist-info/WHEEL
cyber_record_mod-0.1.14.dist-info/entry_points.txt
cyber_record_mod-0.1.14.dist-info/top_level.txt
cyber_record_mod-0.1.14.dist-info/RECORD
