Metadata-Version: 2.4
Name: cyber_record_mod
Version: 0.1.14
Summary: Cyber record offline parse tool(modified for protobuf 5.x)
Home-page: https://github.com/daohu527/cyber_record
Author: daohu527
Author-email: daohu527@gmail.com
Project-URL: Bug Tracker, https://github.com/daohu527/cyber_record/issues
Classifier: Programming Language :: Python :: 3
Classifier: License :: OSI Approved :: Apache Software License
Classifier: Operating System :: OS Independent
Requires-Python: >=3.6
License-File: LICENSE
Requires-Dist: protobuf<6.0.0,>=5.0.0
Requires-Dist: mcap-protobuf-support>=0.1.0
Dynamic: author
Dynamic: author-email
Dynamic: classifier
Dynamic: description
Dynamic: description-content-type
Dynamic: home-page
Dynamic: license-file
Dynamic: project-url
Dynamic: requires-dist
Dynamic: requires-python
Dynamic: summary
